fastapi_core_controllers/__init__.py
fastapi_core_controllers/support_controller.py
rodrigo0000_fastapi_core_controllers-1.0.0.dist-info/METADATA
rodrigo0000_fastapi_core_controllers-1.0.0.dist-info/WHEEL
rodrigo0000_fastapi_core_controllers-1.0.0.dist-info/top_level.txt
rodrigo0000_fastapi_core_controllers-1.0.0.dist-info/RECORD
